[
  {
    "id": 1,
    "title": "Ático moderno frente al Puerto Deportivo",
    "description": "Ático de diseño en el centro de Vilagarcía. Impresionante terraza perimetral con vistas a la ría de Arousa. Edificio de reciente construcción con acabados de alta calidad.",
    "operation": "rent",
    "type": "apartment",
    "price": 1100,
    "favorite": false,
    "location": "Centro - Marina",
    "address": "Avenida de la Marina, 30",
    "city": "Vilagarcía de Arousa",
    "state": "Galicia",
    "zipCode": "36600",
    "coordinates": { "lat": 42.5971, "lng": -8.7645 },
    "rooms": 3,
    "bathrooms": 2,
    "squareMeters": 120,
    "floor": 7,
    "elevator": true,
    "parking": true,
    "terrace": true,
    "yearBuilt": 2019,
    "yearRenovated": null,
    "energyEfficiency": "A",
    "images": [
      "/images/properties/9/vilagarcia_atico.png",
      "/images/properties/9/vilagarcia_atico2.png"

    ],
    "features": ["Sistema de aerotermia", "Terraza de 40m2", "Garaje doble", "Cocina americana"],
    "agencyId": "AG067",
    "publishedDate": "2026-01-29"
  },
  {
    "id": 2,
    "title": "Dúplex luminoso en la zona universitaria",
    "description": "Dúplex seminuevo con mucha luz natural. Totalmente exterior, situado en una zona tranquila con todos los servicios y excelentes comunicaciones.",
    "operation": "rent",
    "type": "apartment",
    "price": 950,
    "favorite": false,
    "location": "Campus Sur - Santa Marta",
    "address": "Avenida de Barcelona, 8",
    "city": "Santiago de Compostela",
    "state": "Galicia",
    "zipCode": "15706",
    "coordinates": { "lat": 42.8715, "lng": -8.5582 },
    "rooms": 3,
    "bathrooms": 2,
    "squareMeters": 110,
    "floor": 5,
    "elevator": true,
    "parking": true,
    "terrace": true,
    "yearBuilt": 2015,
    "yearRenovated": null,
    "energyEfficiency": "C",
    "images": ["/images/properties/6/duplex6.png"],
    "features": ["Vistas despejadas", "Trastero", "Armarios empotrados", "Cocina equipada"],
    "agencyId": "AG012",
    "publishedDate": "2026-01-29"
  },
  {
    "id": 3,
    "title": "Apartamento exclusivo en la Isla de La Toja",
    "description": "Vivienda de lujo en la urbanización más prestigiosa de Galicia. Vistas directas a la ría, acceso a campos de golf y zonas termales. Seguridad 24h y entorno inigualable.",
    "operation": "sale",
    "type": "apartment",
    "price": 450000,
    "favorite": false,
    "location": "Illa da Toxa",
    "address": "Calle Cortegada, 4",
    "city": "O Grove",
    "state": "Galicia",
    "zipCode": "36991",
    "coordinates": { "lat": 42.4892, "lng": -8.8456 },
    "rooms": 2,
    "bathrooms": 2,
    "squareMeters": 90,
    "floor": 2,
    "elevator": true,
    "parking": true,
    "terrace": true,
    "yearBuilt": 2005,
    "yearRenovated": 2024,
    "energyEfficiency": "B",
    "images": ["/images/properties/7/latoja_vistas.png"],
    "features": ["Piscina comunitaria", "Vigilancia privada", "Vistas al mar", "Pista de tenis"],
    "agencyId": "AG055",
    "publishedDate": "2026-01-22"
  },
  {
    "id": 4,
    "title": "Chalet de diseño con piscina cerca de las Termas",
    "description": "Impresionante casa unifamiliar de arquitectura moderna. Cuenta con grandes ventanales con vistas panorámicas al río Miño. Máxima eficiencia energética y acabados premium.",
    "operation": "sale",
    "type": "house",
    "price": 495000,
    "favorite": false,
    "location": "A Chavasqueira",
    "address": "Rúa do Progreso, 110",
    "city": "Ourense",
    "state": "Galicia",
    "zipCode": "32001",
    "coordinates": { "lat": 42.3489, "lng": -7.8633 },
    "rooms": 4,
    "bathrooms": 3,
    "squareMeters": 210,
    "floor": 0,
    "elevator": false,
    "parking": true,
    "terrace": true,
    "yearBuilt": 2024,
    "yearRenovated": null,
    "energyEfficiency": "A",
    "images": [
      "/images/properties/4/ourense_exterior.png",
      "/images/properties/4/ourense_exterior2.png"
    ],
    "features": ["Piscina infinita", "Suelo radiante", "Placas solares", "Garaje para dos coches"],
    "agencyId": "AG044",
    "publishedDate": "2026-01-25"
  },
  {
    "id": 5,
    "title": "Apartamento histórico restaurado en la zona vieja",
    "description": "Encantador apartamento con vigas de madera vistas y muros de piedra originales. A pocos pasos de la Catedral. Ideal para vivienda habitual o inversión turística.",
    "operation": "sale",
    "type": "apartment",
    "price": 275000,
    "favorite": false,
    "location": "Casco Histórico",
    "address": "Rúa do Vilar, 25",
    "city": "Santiago de Compostela",
    "state": "Galicia",
    "zipCode": "15705",
    "coordinates": { "lat": 42.8801, "lng": -8.5457 },
    "rooms": 2,
    "bathrooms": 1,
    "squareMeters": 70,
    "floor": 2,
    "elevator": false,
    "parking": false,
    "terrace": false,
    "yearBuilt": 1890,
    "yearRenovated": 2022,
    "energyEfficiency": "E",
    "images": [
      "/images/properties/5/santiago_interior5.png",
       "/images/properties/5/habitacion5.png",
       "/images/properties/5/baño5.png"
    ],
    "features": ["Piedra vista", "Balcón tradicional", "Ubicación privilegiada", "Techos altos"],
    "agencyId": "AG012",
    "publishedDate": "2026-01-28"
  },
  {
    "id": 6,
    "title": "Hermosa casa con precioso jardin",
    "description": "Increíble ático de diseño con terraza de 40m2. Vistas panorámicas de Barcelona. Totalmente equipado.",
    "operation": "sale",
    "type": "penthouse",
    "price": 780000,
    "favorite": false,
    "location": "Eixample Dreta, Barcelona",
    "address": "Calle Balmes, 234",
    "city": "Barcelona",
    "state": "Barcelona",
    "zipCode": "08006",
    "coordinates": { "lat": 41.3974, "lng": 2.1593 },
    "rooms": 4,
    "bathrooms": 3,
    "squareMeters": 140,
    "floor": 7,
    "elevator": true,
    "parking": true,
    "terrace": true,
    "yearBuilt": 1970,
    "yearRenovated": 2023,
    "energyEfficiency": "A",
    "images": [
      "/images/properties/2/apart1_exterior.png",
      "/images/properties/2/apart1_interior.png"
    ],
    "features": ["Aire acondicionado", "Calefacción", "Sistema de domótica", "Jacuzzi", "Cocina equipada"],
    "agencyId": "AG002",
    "publishedDate": "2024-12-20"
  },
  {
    "id": 7,
    "title": "Moderno apartamento en alquiler",
    "description": "Apartamento de 1 dormitorio recién reformado. Perfecto para estudiantes o jóvenes profesionales. Zona universitaria.",
    "operation": "rent",
    "type": "apartment",
    "price": 850,
    "favorite": false,
    "location": "Chamberí, Madrid",
    "address": "Calle Fuencarral, 89",
    "city": "Madrid",
    "state": "Madrid",
    "zipCode": "28010",
    "coordinates": { "lat": 40.4312, "lng": -3.7019 },
    "rooms": 1,
    "bathrooms": 1,
    "squareMeters": 45,
    "floor": 2,
    "elevator": true,
    "parking": false,
    "terrace": false,
    "yearBuilt": 1985,
    "yearRenovated": 2023,
    "energyEfficiency": "D",
    "images": [
      "/images/properties/3/atico1_terraza.png",
      "/images/properties/3/atico2_terraza.png"
    ],
    "features": ["Amueblado", "Aire acondicionado", "Internet incluido"],
    "agencyId": "AG001",
    "publishedDate": "2025-01-05"
  },
  {
    "id": 8,
    "title": "Casa de piedra con viñedo de Albariño",
    "description": "Propiedad típica gallega en la capital del vino Albariño. Cuenta con un pequeño viñedo propio y una bodega tradicional de piedra. A un paso de la Plaza de Fefiñáns.",
    "operation": "sale",
    "type": "house",
    "price": 315000,
    "favorite": false,
    "location": "Centro Histórico",
    "address": "Rúa de Dona Mariña, 15",
    "city": "Cambados",
    "state": "Galicia",
    "zipCode": "36630",
    "coordinates": { "lat": 42.5153, "lng": -8.8142 },
    "rooms": 4,
    "bathrooms": 2,
    "squareMeters": 215,
    "floor": 0,
    "elevator": false,
    "parking": true,
    "terrace": true,
    "yearBuilt": 1940,
    "yearRenovated": 2015,
    "energyEfficiency": "E",
    "images": [
      "/images/properties/8/cambados_casa.png",
      "/images/properties/8/cambados_casa2.png"
    ],
    "features": ["Viñedo privado", "Bodega", "Barbacoa de piedra", "Suelos de madera de castaño"],
    "agencyId": "AG055",
    "publishedDate": "2026-01-27"
  },
  {
    "id": 9,
    "title": "Luminoso apartamento en el centro de Madrid",
    "description": "Amplio apartamento totalmente reformado en el corazón de la ciudad. Cerca de Gran Vía y Sol. Ideal para familias o profesionales.",
    "operation": "sale",
    "type": "apartment",
    "price": 425000,
    "favorite": false,
    "location": "Malasaña, Madrid",
    "address": "Calle del Pez, 15",
    "city": "Madrid",
    "state": "Madrid",
    "zipCode": "28004",
    "coordinates": { "lat": 40.4254, "lng": -3.7038 },
    "rooms": 3,
    "bathrooms": 2,
    "squareMeters": 95,
    "floor": 3,
    "elevator": true,
    "parking": false,
    "terrace": true,
    "yearBuilt": 1960,
    "yearRenovated": 2022,
    "energyEfficiency": "C",
    "images": [
      "/images/properties/1/piso1_salon.jpg",
      "/images/properties/1/piso1_cocina.jpg",
      "/images/properties/1/piso1_habitacion.jpg"
    ],
    "features": ["Aire acondicionado", "Calefacción central", "Armarios empotrados", "Ventanas climalit"],
    "agencyId": "AG001",
    "publishedDate": "2024-12-15"
  }
]